[
  { "id":  1, "priority": 1, "action": { "type": "block" }, "condition": { "urlFilter": "||popads.net^",           "resourceTypes": ["script","sub_frame","xmlhttprequest","image","media","other","ping"] } },
  { "id":  2, "priority": 1, "action": { "type": "block" }, "condition": { "urlFilter": "||popcash.net^",          "resourceTypes": ["script","sub_frame","xmlhttprequest","image","media","other","ping"] } },
  { "id":  3, "priority": 1, "action": { "type": "block" }, "condition": { "urlFilter": "||exoclick.com^",         "resourceTypes": ["script","sub_frame","xmlhttprequest","image","media","other","ping"] } },
  { "id":  4, "priority": 1, "action": { "type": "block" }, "condition": { "urlFilter": "||trafficjunky.net^",     "resourceTypes": ["script","sub_frame","xmlhttprequest","image","media","other","ping"] } },
  { "id":  5, "priority": 1, "action": { "type": "block" }, "condition": { "urlFilter": "||juicyads.com^",         "resourceTypes": ["script","sub_frame","xmlhttprequest","image","media","other","ping"] } },
  { "id":  6, "priority": 1, "action": { "type": "block" }, "condition": { "urlFilter": "||hilltopads.net^",       "resourceTypes": ["script","sub_frame","xmlhttprequest","image","media","other","ping"] } },
  { "id":  7, "priority": 1, "action": { "type": "block" }, "condition": { "urlFilter": "||adspyglass.com^",       "resourceTypes": ["script","sub_frame","xmlhttprequest","image","media","other","ping"] } },
  { "id":  8, "priority": 1, "action": { "type": "block" }, "condition": { "urlFilter": "||propellerads.com^",     "resourceTypes": ["script","sub_frame","xmlhttprequest","image","media","other","ping"] } },
  { "id":  9, "priority": 1, "action": { "type": "block" }, "condition": { "urlFilter": "||adsterra.com^",         "resourceTypes": ["script","sub_frame","xmlhttprequest","image","media","other","ping"] } },
  { "id": 10, "priority": 1, "action": { "type": "block" }, "condition": { "urlFilter": "||clickadu.com^",         "resourceTypes": ["script","sub_frame","xmlhttprequest","image","media","other","ping"] } },
  { "id": 11, "priority": 1, "action": { "type": "block" }, "condition": { "urlFilter": "||adnium.com^",           "resourceTypes": ["script","sub_frame","xmlhttprequest","image","media","other","ping"] } },
  { "id": 12, "priority": 1, "action": { "type": "block" }, "condition": { "urlFilter": "||adskeeper.co.uk^",      "resourceTypes": ["script","sub_frame","xmlhttprequest","image","media","other","ping"] } },
  { "id": 13, "priority": 1, "action": { "type": "block" }, "condition": { "urlFilter": "||push.pub^",             "resourceTypes": ["script","sub_frame","xmlhttprequest","image","media","other","ping"] } },
  { "id": 14, "priority": 1, "action": { "type": "block" }, "condition": { "urlFilter": "||traffichunt.com^",      "resourceTypes": ["script","sub_frame","xmlhttprequest","image","media","other","ping"] } },
  { "id": 15, "priority": 1, "action": { "type": "block" }, "condition": { "urlFilter": "||revcontent.com^",       "resourceTypes": ["script","sub_frame","xmlhttprequest","image","media","other","ping"] } },
  { "id": 16, "priority": 1, "action": { "type": "block" }, "condition": { "urlFilter": "||mgid.com^",             "resourceTypes": ["script","sub_frame","xmlhttprequest","image","media","other","ping"] } },
  { "id": 17, "priority": 1, "action": { "type": "block" }, "condition": { "urlFilter": "||bidvertiser.com^",      "resourceTypes": ["script","sub_frame","xmlhttprequest","image","media","other","ping"] } },
  { "id": 18, "priority": 1, "action": { "type": "block" }, "condition": { "urlFilter": "||adcash.com^",           "resourceTypes": ["script","sub_frame","xmlhttprequest","image","media","other","ping"] } },
  { "id": 19, "priority": 1, "action": { "type": "block" }, "condition": { "urlFilter": "||mylead.global^",        "resourceTypes": ["script","sub_frame","xmlhttprequest","image","media","other","ping"] } },
  { "id": 20, "priority": 1, "action": { "type": "block" }, "condition": { "urlFilter": "||richpush.co^",          "resourceTypes": ["script","sub_frame","xmlhttprequest","image","media","other","ping"] } },
  { "id": 21, "priority": 1, "action": { "type": "block" }, "condition": { "urlFilter": "||pushground.com^",       "resourceTypes": ["script","sub_frame","xmlhttprequest","image","media","other","ping"] } },
  { "id": 22, "priority": 1, "action": { "type": "block" }, "condition": { "urlFilter": "||monetizer101.com^",     "resourceTypes": ["script","sub_frame","xmlhttprequest","image","media","other","ping"] } },
  { "id": 23, "priority": 1, "action": { "type": "block" }, "condition": { "urlFilter": "||adpushup.com^",         "resourceTypes": ["script","sub_frame","xmlhttprequest","image","media","other","ping"] } },
  { "id": 24, "priority": 1, "action": { "type": "block" }, "condition": { "urlFilter": "||trafficfactory.biz^",   "resourceTypes": ["script","sub_frame","xmlhttprequest","image","media","other","ping"] } },
  { "id": 25, "priority": 1, "action": { "type": "block" }, "condition": { "urlFilter": "||adfly.com^",            "resourceTypes": ["script","sub_frame","xmlhttprequest","image","media","other","ping"] } },
  { "id": 26, "priority": 1, "action": { "type": "block" }, "condition": { "urlFilter": "||adf.ly^",               "resourceTypes": ["script","sub_frame","xmlhttprequest","image","media","other","ping"] } },
  { "id": 27, "priority": 1, "action": { "type": "block" }, "condition": { "urlFilter": "||go2ads.net^",           "resourceTypes": ["script","sub_frame","xmlhttprequest","image","media","other","ping"] } },
  { "id": 28, "priority": 1, "action": { "type": "block" }, "condition": { "urlFilter": "||cutwin.com^",           "resourceTypes": ["script","sub_frame","xmlhttprequest","image","media","other","ping"] } },
  { "id": 29, "priority": 1, "action": { "type": "block" }, "condition": { "urlFilter": "||openload.co^",          "resourceTypes": ["script","sub_frame","xmlhttprequest","other","ping"] } },
  { "id": 30, "priority": 1, "action": { "type": "block" }, "condition": { "urlFilter": "||doubleclick.net^",      "resourceTypes": ["script","sub_frame","xmlhttprequest","image","other","ping"] } },
  { "id": 31, "priority": 1, "action": { "type": "block" }, "condition": { "urlFilter": "||googlesyndication.com^","resourceTypes": ["script","sub_frame","xmlhttprequest","image","other","ping"] } },
  { "id": 32, "priority": 1, "action": { "type": "block" }, "condition": { "urlFilter": "||moonicorn.network^",    "resourceTypes": ["script","sub_frame","xmlhttprequest","image","media","other","ping"] } },
  { "id": 33, "priority": 1, "action": { "type": "block" }, "condition": { "urlFilter": "||adwareremovaltool.com^","resourceTypes": ["script","sub_frame","xmlhttprequest","image","media","other","ping"] } },
  { "id": 34, "priority": 1, "action": { "type": "block" }, "condition": { "urlFilter": "||ad-maven.com^",         "resourceTypes": ["script","sub_frame","xmlhttprequest","image","media","other","ping"] } },
  { "id": 35, "priority": 1, "action": { "type": "block" }, "condition": { "urlFilter": "||admaven.com^",          "resourceTypes": ["script","sub_frame","xmlhttprequest","image","media","other","ping"] } },
  { "id": 36, "priority": 1, "action": { "type": "block" }, "condition": { "urlFilter": "||popunder.ru^",          "resourceTypes": ["script","sub_frame","xmlhttprequest","image","media","other","ping"] } },
  { "id": 37, "priority": 1, "action": { "type": "block" }, "condition": { "urlFilter": "||clkmon.com^",           "resourceTypes": ["script","sub_frame","xmlhttprequest","image","media","other","ping"] } },
  { "id": 38, "priority": 1, "action": { "type": "block" }, "condition": { "urlFilter": "||adtelligent.com^",      "resourceTypes": ["script","sub_frame","xmlhttprequest","image","media","other","ping"] } },
  { "id": 39, "priority": 1, "action": { "type": "block" }, "condition": { "urlFilter": "||etargetnet.com^",       "resourceTypes": ["script","sub_frame","xmlhttprequest","image","media","other","ping"] } },
  { "id": 40, "priority": 1, "action": { "type": "block" }, "condition": { "urlFilter": "||smartadserver.com^",    "resourceTypes": ["script","sub_frame","xmlhttprequest","image","media","other","ping"] } }
]
